<?xml version="1.0" standalone="yes"?>
<NewDataSet>
  <xs:schema id="NewDataSet" xmlns="" xmlns:xs="http://www.w3.org/2001/XMLSchema" xmlns:msdata="urn:schemas-microsoft-com:xml-msdata">
    <xs:element name="NewDataSet" msdata:IsDataSet="true" msdata:MainDataTable="marketintervaldetail" msdata:UseCurrentLocale="true">
      <xs:complexType>
        <xs:choice minOccurs="0" maxOccurs="unbounded">
          <xs:element name="marketintervaldetail">
            <xs:complexType>
              <xs:sequence>
                <xs:element name="Data" type="xs:string" minOccurs="0" />
                <xs:element name="Mercato" type="xs:string" minOccurs="0" />
                <xs:element name="Ora" type="xs:string" minOccurs="0" />
                <xs:element name="Totale" type="xs:string" minOccurs="0" />
                <xs:element name="CNOR" type="xs:string" minOccurs="0" />
                <xs:element name="CSUD" type="xs:string" minOccurs="0" />
                <xs:element name="NORD" type="xs:string" minOccurs="0" />
                <xs:element name="SARD" type="xs:string" minOccurs="0" />
                <xs:element name="SICI" type="xs:string" minOccurs="0" />
                <xs:element name="SUD" type="xs:string" minOccurs="0" />
              </xs:sequence>
            </xs:complexType>
          </xs:element>
        </xs:choice>
      </xs:complexType>
    </xs:element>
  </xs:schema>
  <marketintervaldetail>
    <Data>20170202</Data>
    <Mercato>MGP</Mercato>
    <Ora>01</Ora>
    <Totale>28752</Totale>
    <CNOR>3277</CNOR>
    <CSUD>4402</CSUD>
    <NORD>15869</NORD>
    <SARD>869</SARD>
    <SICI>1790</SICI>
    <SUD>2545</SUD>
  </marketintervaldetail>
  <marketintervaldetail>
    <Data>20170202</Data>
    <Mercato>MGP</Mercato>
    <Ora>02</Ora>
    <Totale>26983</Totale>
    <CNOR>2995</CNOR>
    <CSUD>4098</CSUD>
    <NORD>15034</NORD>
    <SARD>788</SARD>
    <SICI>1565</SICI>
    <SUD>2503</SUD>
  </marketintervaldetail>
  <marketintervaldetail>
    <Data>20170202</Data>
    <Mercato>MGP</Mercato>
    <Ora>03</Ora>
    <Totale>26042</Totale>
    <CNOR>2870</CNOR>
    <CSUD>3916</CSUD>
    <NORD>14727</NORD>
    <SARD>753</SARD>
    <SICI>1486</SICI>
    <SUD>2290</SUD>
  </marketintervaldetail>
  <marketintervaldetail>
    <Data>20170202</Data>
    <Mercato>MGP</Mercato>
    <Ora>04</Ora>
    <Totale>25838</Totale>
    <CNOR>2818</CNOR>
    <CSUD>3819</CSUD>
    <NORD>14733</NORD>
    <SARD>742</SARD>
    <SICI>1479</SICI>
    <SUD>2247</SUD>
  </marketintervaldetail>
  <marketintervaldetail>
    <Data>20170202</Data>
    <Mercato>MGP</Mercato>
    <Ora>05</Ora>
    <Totale>26116</Totale>
    <CNOR>2817</CNOR>
    <CSUD>3793</CSUD>
    <NORD>15040</NORD>
    <SARD>723</SARD>
    <SICI>1471</SICI>
    <SUD>2272</SUD>
  </marketintervaldetail>
  <marketintervaldetail>
    <Data>20170202</Data>
    <Mercato>MGP</Mercato>
    <Ora>06</Ora>
    <Totale>27776</Totale>
    <CNOR>3067</CNOR>
    <CSUD>3972</CSUD>
    <NORD>15939</NORD>
    <SARD>769</SARD>
    <SICI>1556</SICI>
    <SUD>2473</SUD>
  </marketintervaldetail>
  <marketintervaldetail>
    <Data>20170202</Data>
    <Mercato>MGP</Mercato>
    <Ora>07</Ora>
    <Totale>33014</Totale>
    <CNOR>3507</CNOR>
    <CSUD>4738</CSUD>
    <NORD>19263</NORD>
    <SARD>885</SARD>
    <SICI>1755</SICI>
    <SUD>2866</SUD>
  </marketintervaldetail>
  <marketintervaldetail>
    <Data>20170202</Data>
    <Mercato>MGP</Mercato>
    <Ora>08</Ora>
    <Totale>39791</Totale>
    <CNOR>4131</CNOR>
    <CSUD>5698</CSUD>
    <NORD>23571</NORD>
    <SARD>1087</SARD>
    <SICI>2099</SICI>
    <SUD>3205</SUD>
  </marketintervaldetail>
  <marketintervaldetail>
    <Data>20170202</Data>
    <Mercato>MGP</Mercato>
    <Ora>09</Ora>
    <Totale>44507</Totale>
    <CNOR>4745</CNOR>
    <CSUD>6348</CSUD>
    <NORD>26469</NORD>
    <SARD>1143</SARD>
    <SICI>2311</SICI>
    <SUD>3491</SUD>
  </marketintervaldetail>
  <marketintervaldetail>
    <Data>20170202</Data>
    <Mercato>MGP</Mercato>
    <Ora>10</Ora>
    <Totale>46764</Totale>
    <CNOR>5119</CNOR>
    <CSUD>6965</CSUD>
    <NORD>27694</NORD>
    <SARD>1122</SARD>
    <SICI>2396</SICI>
    <SUD>3468</SUD>
  </marketintervaldetail>
  <marketintervaldetail>
    <Data>20170202</Data>
    <Mercato>MGP</Mercato>
    <Ora>11</Ora>
    <Totale>46621</Totale>
    <CNOR>5135</CNOR>
    <CSUD>7166</CSUD>
    <NORD>27647</NORD>
    <SARD>1067</SARD>
    <SICI>2346</SICI>
    <SUD>3260</SUD>
  </marketintervaldetail>
  <marketintervaldetail>
    <Data>20170202</Data>
    <Mercato>MGP</Mercato>
    <Ora>12</Ora>
    <Totale>45937</Totale>
    <CNOR>5227</CNOR>
    <CSUD>6910</CSUD>
    <NORD>27351</NORD>
    <SARD>1009</SARD>
    <SICI>2186</SICI>
    <SUD>3254</SUD>
  </marketintervaldetail>
  <marketintervaldetail>
    <Data>20170202</Data>
    <Mercato>MGP</Mercato>
    <Ora>13</Ora>
    <Totale>43747</Totale>
    <CNOR>5066</CNOR>
    <CSUD>6572</CSUD>
    <NORD>25648</NORD>
    <SARD>990</SARD>
    <SICI>2206</SICI>
    <SUD>3265</SUD>
  </marketintervaldetail>
  <marketintervaldetail>
    <Data>20170202</Data>
    <Mercato>MGP</Mercato>
    <Ora>14</Ora>
    <Totale>43024</Totale>
    <CNOR>4804</CNOR>
    <CSUD>6401</CSUD>
    <NORD>25447</NORD>
    <SARD>973</SARD>
    <SICI>2172</SICI>
    <SUD>3227</SUD>
  </marketintervaldetail>
  <marketintervaldetail>
    <Data>20170202</Data>
    <Mercato>MGP</Mercato>
    <Ora>15</Ora>
    <Totale>43870</Totale>
    <CNOR>5080</CNOR>
    <CSUD>6345</CSUD>
    <NORD>25926</NORD>
    <SARD>974</SARD>
    <SICI>2224</SICI>
    <SUD>3321</SUD>
  </marketintervaldetail>
  <marketintervaldetail>
    <Data>20170202</Data>
    <Mercato>MGP</Mercato>
    <Ora>16</Ora>
    <Totale>44547</Totale>
    <CNOR>5175</CNOR>
    <CSUD>6457</CSUD>
    <NORD>26221</NORD>
    <SARD>996</SARD>
    <SICI>2258</SICI>
    <SUD>3440</SUD>
  </marketintervaldetail>
  <marketintervaldetail>
    <Data>20170202</Data>
    <Mercato>MGP</Mercato>
    <Ora>17</Ora>
    <Totale>45275</Totale>
    <CNOR>5129</CNOR>
    <CSUD>6387</CSUD>
    <NORD>26663</NORD>
    <SARD>989</SARD>
    <SICI>2461</SICI>
    <SUD>3646</SUD>
  </marketintervaldetail>
  <marketintervaldetail>
    <Data>20170202</Data>
    <Mercato>MGP</Mercato>
    <Ora>18</Ora>
    <Totale>45706</Totale>
    <CNOR>4999</CNOR>
    <CSUD>6679</CSUD>
    <NORD>26456</NORD>
    <SARD>1065</SARD>
    <SICI>2593</SICI>
    <SUD>3914</SUD>
  </marketintervaldetail>
  <marketintervaldetail>
    <Data>20170202</Data>
    <Mercato>MGP</Mercato>
    <Ora>19</Ora>
    <Totale>46788</Totale>
    <CNOR>4999</CNOR>
    <CSUD>7171</CSUD>
    <NORD>26479</NORD>
    <SARD>1207</SARD>
    <SICI>2829</SICI>
    <SUD>4103</SUD>
  </marketintervaldetail>
  <marketintervaldetail>
    <Data>20170202</Data>
    <Mercato>MGP</Mercato>
    <Ora>20</Ora>
    <Totale>46056</Totale>
    <CNOR>4862</CNOR>
    <CSUD>7309</CSUD>
    <NORD>25648</NORD>
    <SARD>1272</SARD>
    <SICI>2904</SICI>
    <SUD>4061</SUD>
  </marketintervaldetail>
  <marketintervaldetail>
    <Data>20170202</Data>
    <Mercato>MGP</Mercato>
    <Ora>21</Ora>
    <Totale>43655</Totale>
    <CNOR>4434</CNOR>
    <CSUD>7084</CSUD>
    <NORD>23901</NORD>
    <SARD>1269</SARD>
    <SICI>2900</SICI>
    <SUD>4067</SUD>
  </marketintervaldetail>
  <marketintervaldetail>
    <Data>20170202</Data>
    <Mercato>MGP</Mercato>
    <Ora>22</Ora>
    <Totale>40360</Totale>
    <CNOR>4154</CNOR>
    <CSUD>6565</CSUD>
    <NORD>21904</NORD>
    <SARD>1186</SARD>
    <SICI>2740</SICI>
    <SUD>3811</SUD>
  </marketintervaldetail>
  <marketintervaldetail>
    <Data>20170202</Data>
    <Mercato>MGP</Mercato>
    <Ora>23</Ora>
    <Totale>36200</Totale>
    <CNOR>3722</CNOR>
    <CSUD>5974</CSUD>
    <NORD>19465</NORD>
    <SARD>1085</SARD>
    <SICI>2514</SICI>
    <SUD>3440</SUD>
  </marketintervaldetail>
  <marketintervaldetail>
    <Data>20170202</Data>
    <Mercato>MGP</Mercato>
    <Ora>24</Ora>
    <Totale>32495</Totale>
    <CNOR>3448</CNOR>
    <CSUD>5231</CSUD>
    <NORD>17554</NORD>
    <SARD>963</SARD>
    <SICI>2208</SICI>
    <SUD>3091</SUD>
  </marketintervaldetail>
</NewDataSet>